{
  "hash": "8eb8425c",
  "configHash": "8e0280ff",
  "lockfileHash": "1c61d738",
  "browserHash": "312791ea",
  "optimized": {
    "react-dom/client": {
      "src": "../../node_modules/react-dom/client.js",
      "file": "react-dom_client.js",
      "fileHash": "6892a809",
      "needsInterop": true
    },
    "react-scrollbars-custom": {
      "src": "../../node_modules/react-scrollbars-custom/dist/rsc.esm.js",
      "file": "react-scrollbars-custom.js",
      "fileHash": "07e01d53",
      "needsInterop": false
    }
  },
  "chunks": {
    "chunk-5J73OJKA": {
      "file": "chunk-5J73OJKA.js"
    }
  }
}